mfconnect/__init__.py
mfconnect/meteo.py
mfconnect/meteo_completion
mfconnect/meteorc
mfconnect/version.py
mfconnect-0.0.398.dist-info/LICENCE
mfconnect-0.0.398.dist-info/METADATA
mfconnect-0.0.398.dist-info/WHEEL
mfconnect-0.0.398.dist-info/entry_points.txt
mfconnect-0.0.398.dist-info/top_level.txt
mfconnect-0.0.398.dist-info/RECORD
