Metadata-Version: 2.1
Name: mfconnect
Version: 0.0.398
Summary: mfconnect simplifies telnet and ftp connections to Meteo France HPC servers thru the MF gateway.
Home-page: https://gitlab.mercator-ocean.fr/internal/mfconnect
Author: Matthieu Clavier
Author-email: mclavier@mercator-ocean.fr
License: BSD Licence
Project-URL: Repository, https://gitlab.mercator-ocean.fr/internal/mfconnect
Classifier: Development Status :: 4 - Beta
Classifier: Intended Audience :: Science/Research
Classifier: Topic :: Scientific/Engineering
Classifier: Topic :: Terminals :: Telnet
Classifier: Environment :: Console
Classifier: Programming Language :: Python :: 3.6
Classifier: License :: OSI Approved :: BSD License
Requires-Python: >=3.6,<3.9
License-File: LICENCE
Requires-Dist: pexpect >=4.8.0
Requires-Dist: pyyaml ==5.3.1
Requires-Dist: namedtupled ==0.3.3
